convx.py
main.py
convx-0.1.4.dist-info/LICENSE.txt
convx-0.1.4.dist-info/METADATA
convx-0.1.4.dist-info/WHEEL
convx-0.1.4.dist-info/entry_points.txt
convx-0.1.4.dist-info/top_level.txt
convx-0.1.4.dist-info/RECORD
