Metadata-Version: 2.1
Name: convx
Version: 0.1.4
Summary: A package for quickly converting binary, hex and decimal to one another.
Home-page: https://github.com/The-Real-Thisas/convx
Author: Thisas
Author-email: thisas@thisas.dev
License: UNKNOWN
Platform: UNKNOWN
Classifier: Programming Language :: Python :: 3
Classifier: Programming Language :: Python :: 3.6
Classifier: Programming Language :: Python :: 3.7
Classifier: License :: OSI Approved :: MIT License
Classifier: Operating System :: OS Independent
Requires-Dist: riposte (>=0.4.1)
Provides-Extra: dev
Requires-Dist: pytest (>=6.2.4) ; extra == 'dev'
